quetzal_client-0.5.3-py3.7-nspkg.pth
quetzal/client/__init__.py
quetzal/client/_version.py
quetzal/client/base.py
quetzal/client/config.py
quetzal/client/exceptions.py
quetzal/client/utils.py
quetzal/client/cli/__init__.py
quetzal/client/cli/_progress.py
quetzal/client/cli/auth.py
quetzal/client/cli/file.py
quetzal/client/cli/main.py
quetzal/client/cli/query.py
quetzal/client/cli/workspace.py
quetzal/client/helpers/__init__.py
quetzal/client/helpers/auth.py
quetzal/client/helpers/file.py
quetzal/client/helpers/misc.py
quetzal/client/helpers/query.py
quetzal/client/helpers/workspace.py
quetzal_client-0.5.3.dist-info/LICENSE
quetzal_client-0.5.3.dist-info/METADATA
quetzal_client-0.5.3.dist-info/WHEEL
quetzal_client-0.5.3.dist-info/entry_points.txt
quetzal_client-0.5.3.dist-info/namespace_packages.txt
quetzal_client-0.5.3.dist-info/top_level.txt
quetzal_client-0.5.3.dist-info/RECORD
